youtube_autonomous/__init__.py
youtube_autonomous/youtube_autonomous.py
youtube_autonomous/config/__init__.py
youtube_autonomous/database/__init__.py
youtube_autonomous/database/database_handler.py
youtube_autonomous/elements/__init__.py
youtube_autonomous/elements/enhancement.py
youtube_autonomous/elements/segment.py
youtube_autonomous/elements/builder/__init__.py
youtube_autonomous/elements/builder/ai_image_element_builder.py
youtube_autonomous/elements/builder/ai_video_element_builder.py
youtube_autonomous/elements/builder/custom_stock_element_builder.py
youtube_autonomous/elements/builder/effect_element_builder.py
youtube_autonomous/elements/builder/element_builder.py
youtube_autonomous/elements/builder/enums.py
youtube_autonomous/elements/builder/greenscreen_element_builder.py
youtube_autonomous/elements/builder/image_element_builder.py
youtube_autonomous/elements/builder/meme_element_builder.py
youtube_autonomous/elements/builder/premade_element_builder.py
youtube_autonomous/elements/builder/sound_element_builder.py
youtube_autonomous/elements/builder/stock_element_builder.py
youtube_autonomous/elements/builder/text_element_builder.py
youtube_autonomous/elements/builder/video_element_builder.py
youtube_autonomous/elements/builder/youtube_video_element_builder.py
youtube_autonomous/elements/rules/__init__.py
youtube_autonomous/elements/rules/ai_image_element_rules.py
youtube_autonomous/elements/rules/ai_video_element_rules.py
youtube_autonomous/elements/rules/custom_stock_element_rules.py
youtube_autonomous/elements/rules/effect_element_rules.py
youtube_autonomous/elements/rules/element_rules.py
youtube_autonomous/elements/rules/greenscreen_element_rules.py
youtube_autonomous/elements/rules/image_element_rules.py
youtube_autonomous/elements/rules/meme_element_rules.py
youtube_autonomous/elements/rules/premade_element_rules.py
youtube_autonomous/elements/rules/rules_checker.py
youtube_autonomous/elements/rules/sound_element_rules.py
youtube_autonomous-0.0.74.dist-info/LICENSE
youtube_autonomous-0.0.74.dist-info/METADATA
youtube_autonomous-0.0.74.dist-info/WHEEL
youtube_autonomous-0.0.74.dist-info/top_level.txt
youtube_autonomous-0.0.74.dist-info/RECORD
