Metadata-Version: 2.1
Name: youtube-autonomous
Version: 0.0.74
Summary: Youtube Autonomous main software.
Home-page: UNKNOWN
Author: Daniel Alcalá
Author-email: <danielalcalavalera@gmail.com>
License: UNKNOWN
Keywords: youtube autonomous main software
Platform: UNKNOWN
Classifier: Development Status :: 3 - Alpha
Classifier: Intended Audience :: Education
Classifier: Programming Language :: Python :: 2
Classifier: Programming Language :: Python :: 3
Classifier: Operating System :: MacOS :: MacOS X
Classifier: Operating System :: Microsoft :: Windows
Requires-Dist: yta-multimedia
Requires-Dist: yta-general-utils
Requires-Dist: youtubeenhanced
Requires-Dist: yta-stock-downloader
